[
  {
    "id": 0,
    "email": "admin",
    "password": "admin"
  },
  {
    "id": 1,
    "firstName": "Jeremy",
    "lastName": "Zanna",
    "email": "zanna.jeremy@gmail.com",
    "password": "12345",
    "posts": [
      {
        "postId": 2,
        "userName": "Jeremy Zanna",
        "title": "",
        "likedBy": [],
        "insertionTime": 7,
        "content": "Mon deuxieme prenom est David."
      },
      {
        "postId": 3,
        "userName": "Jeremy Zanna",
        "title": "",
        "likedBy": [],
        "insertionTime": 10,
        "content": "Je m'appelle Jeremy"
      }
    ],
    "following": [
      2,
      3
    ],
    "lastLogOut": null
  },
  {
    "id": 2,
    "firstName": "Alon",
    "lastName": "Silberstein",
    "email": "alonzilberr@gmail.com",
    "password": "11111",
    "posts": [
      {
        "postId": 0,
        "userName": "Alon Silberstein",
        "title": "",
        "likedBy": [],
        "insertionTime": 0,
        "content": "Ani Alon YA bonjour"
      }
    ],
    "following": [],
    "lastLogOut": null
  },
  {
    "id": 3,
    "firstName": "Dudu",
    "lastName": "Faruk",
    "email": "dudu123@gmail.com",
    "password": "Arak123",
    "posts": [
      {
        "postId": 1,
        "userName": "Dudu Faruk",
        "title": "",
        "likedBy": [],
        "insertionTime": 5,
        "content": "Ani ohev arak"
      }
    ],
    "following": [],
    "lastLogOut": null
  },
  {
    "id": 4,
    "firstName": "Ilan",
    "lastName": "Balouka",
    "email": "fullstack@gmail.com",
    "password": "1234",
    "posts": [],
    "following": [],
    "lastLogOut": null
  }
]